package_mk/__init__.py
package_mk/mk_ai.py
package_mk/mk_dm.py
package_mk-0.1.dist-info/METADATA
package_mk-0.1.dist-info/WHEEL
package_mk-0.1.dist-info/top_level.txt
package_mk-0.1.dist-info/RECORD
