Metadata-Version: 2.1
Name: package_mk
Version: 0.1
Summary: Modul MK Glenn
Home-page: https://github.com/glennhkm/test-pypi.git
Author: Glenn Hakim
Author-email: glenn.hkm@gmail.com
Classifier: Programming Language :: Python :: 3
Classifier: License :: OSI Approved :: MIT License
Classifier: Operating System :: OS Independent
Requires-Python: >=3.6
